sf2cf/__init__.py
sf2cf/sf2cf.py
sf2cf/feeds/__init__.py
sf2cf/feeds/cyanideandhappiness.py
sf2cf/feeds/dilbert.py
sf2cf/feeds/webtoons.py
sf2cf/tests/__init__.py
sf2cf/tests/test_sf2cf.py
sf2cf-0.3.1.dist-info/LICENSE
sf2cf-0.3.1.dist-info/METADATA
sf2cf-0.3.1.dist-info/WHEEL
sf2cf-0.3.1.dist-info/entry_points.txt
sf2cf-0.3.1.dist-info/top_level.txt
sf2cf-0.3.1.dist-info/RECORD
