Metadata-Version: 2.1
Name: sf2cf
Version: 0.3.1
Summary: Improve RSS/Atom feeds
Home-page: https://git.framasoft.org/Steap/sf2cf
Author: Cyril Roelandt
Author-email: tipecaml@gmail.com
License: BSD-3-Clause
Platform: UNKNOWN
Classifier: Development Status :: 3 - Alpha
Classifier: License :: OSI Approved :: BSD License
Classifier: Programming Language :: Python :: 3
Classifier: Programming Language :: Python :: 3.5
Requires-Dist: bs4
Requires-Dist: feedparser
Requires-Dist: lxml
Requires-Dist: pillow
Requires-Dist: requests
